socketcan/__init__.py
socketcan/socketcan.py
socketcan-1.3.0.dist-info/LICENSE
socketcan-1.3.0.dist-info/METADATA
socketcan-1.3.0.dist-info/WHEEL
socketcan-1.3.0.dist-info/top_level.txt
socketcan-1.3.0.dist-info/RECORD
