Metadata-Version: 2.1
Name: socketcan
Version: 1.3.0
Summary: A python 3 interface to socketcan
Author-email: Patrick Menschel <menschel.p@posteo.de>
Project-URL: Homepage, https://gitlab.com/menschel/socketcan
Project-URL: Bug Tracker, https://gitlab.com/menschel/socketcan/issues
Classifier: Programming Language :: Python :: 3
Classifier: Development Status :: 5 - Production/Stable
Classifier: License :: OSI Approved :: GNU General Public License v3 or later (GPLv3+)
Classifier: Operating System :: POSIX :: Linux
Classifier: Intended Audience :: Developers
Classifier: Topic :: Scientific/Engineering
Classifier: Topic :: Software Development :: Embedded Systems
Requires-Python: >=3.9
License-File: LICENSE
Requires-Dist: socketcan
